Metadata-Version: 2.1
Name: gauche
Version: 0.1.5
Summary: Gaussian Process Library for Molecules, Chemical Reactions and Proteins.
License: MIT
Keywords: machine-learning gaussian-processes kernels pytorch chemistry biology protein ligand
Platform: any
Classifier: License :: OSI Approved :: MIT License
Classifier: Development Status :: 5 - Production/Stable
Classifier: Operating System :: Microsoft :: Windows
Classifier: Operating System :: POSIX
Classifier: Operating System :: Unix
Classifier: Operating System :: MacOS
Classifier: Programming Language :: Python :: 3.8
Classifier: Programming Language :: Python :: 3.9
Classifier: Programming Language :: Python :: 3.10
Classifier: Programming Language :: Python :: 3.11
Classifier: Topic :: Scientific/Engineering
Requires-Python: >=3.8
Provides-Extra: rxn
Provides-Extra: graphs
Provides-Extra: dev
Provides-Extra: docs
Provides-Extra: all
License-File: LICENSE
